gpu4pyscf/lib/deps/lib/libxc.so
gpu4pyscf_libxc_cuda12x-0.8.1.dist-info/METADATA
gpu4pyscf_libxc_cuda12x-0.8.1.dist-info/WHEEL
gpu4pyscf_libxc_cuda12x-0.8.1.dist-info/top_level.txt
gpu4pyscf_libxc_cuda12x-0.8.1.dist-info/RECORD
