Metadata-Version: 2.4
Name: gpu4pyscf-libxc-cuda12x
Version: 0.8.1
Summary: Customized LibXC for GPU4PySCF
Author: PySCF developers
License: Apache-2.0
Dynamic: author
Dynamic: license
Dynamic: summary
